projects/__init__.py
pycrash/__init__.py
pycrash/createProject.py
pycrash/definitions.py
pycrash/global_frame.py
pycrash/global_frame_small.py
pycrash/impact_main.py
pycrash/impact_vehicle_model.py
pycrash/impc.py
pycrash/kinematics.py
pycrash/kinematicstwo.py
pycrash/multi_vehicle_model.py
pycrash/plots.py
pycrash/project.py
pycrash/sdof_model.py
pycrash/vehicle.py
pycrash/vehicle_model.py
pycrash/dash/__init__.py
pycrash/dash/app.py
pycrash/data/__init__.py
pycrash/data/archive/__init__.py
pycrash/data/defaults/__init__.py
pycrash/data/defaults/config.py
pycrash/data/defaults/definitions.py
pycrash/functions/CFCFilter.py
pycrash/functions/__init__.py
pycrash/functions/ar.py
pycrash/functions/arPlots.py
pycrash/functions/process_nhtsa_loadcelldata_ascii_ver1.py
pycrash/functions/process_nhtsa_loadcelldata_ascii_ver2.py
pycrash/functions/scratch.py
pycrash/functions/square_wave.py
pycrash/functions/vehicle_stiffness.py
pycrash/model_calcs/__init__.py
pycrash/model_calcs/carpenter_momentum.py
pycrash/model_calcs/carpenter_momentum_calcs.py
pycrash/model_calcs/collision_plane.py
pycrash/model_calcs/impact_detect.py
pycrash/model_calcs/momentum_optimizer.py
pycrash/model_calcs/position_data.py
pycrash/model_calcs/sideswipe.py
pycrash/model_calcs/tire_model.py
pycrash/sdof_calcs/__init__.py
pycrash/sdof_calcs/sdof_calculations.py
pycrash/sdof_calcs/spring_models.py
pycrash/visualization/__init__.py
pycrash/visualization/cg_motion_compare.py
pycrash/visualization/initial_positions.py
pycrash/visualization/kinematics.py
pycrash/visualization/kinematics_compare.py
pycrash/visualization/model.py
pycrash/visualization/model_compare.py
pycrash/visualization/model_interval.py
pycrash/visualization/model_interval_two_vehicles.py
pycrash/visualization/scratch_position.py
pycrash/visualization/sdof_plot.py
pycrash/visualization/tire_details.py
pycrash/visualization/vehicle.py
pycrash/visualization/vehicles_at_impact.py
pycrash-0.0.17.dist-info/LICENSE
pycrash-0.0.17.dist-info/METADATA
pycrash-0.0.17.dist-info/WHEEL
pycrash-0.0.17.dist-info/top_level.txt
pycrash-0.0.17.dist-info/RECORD
