Metadata-Version: 2.1
Name: pycrash
Version: 0.0.17
Summary: software tool for simulating vehicle motion and impacts based on     fundamental physics and accident reconstruction techniques
Home-page: https://github.com/joe-cormier/pycrash
Author: Joe Cormier
Author-email: joemcormier@outlook.com
License: UNKNOWN
Platform: UNKNOWN
Classifier: Programming Language :: Python :: 3
Classifier: License :: OSI Approved :: GNU General Public License v3 (GPLv3)
Classifier: Operating System :: OS Independent
Requires-Python: >=3.6
